{"is_source_file": false, "format": "", "description": "", "external_files": [], "external_methods": [], "published": [], "classes": [], "methods": [], "calls": [], "search-terms": [], "state": 2, "file_id": 2, "knowledge_revision": 15, "git_revision": "b300ba03bfd6c69df0dbc42c56300d84a3819f03", "hash": "d001d53c059625c4bcf75bf5a7f3fcf0", "format-version": 4, "code-base-name": "bus_tracker_frontend", "filename": "bus_tracker_frontend/package.json", "revision_history": [{"15": "b300ba03bfd6c69df0dbc42c56300d84a3819f03"}]}